README
setup.py
kuaipandriver/__init__.py
kuaipandriver/common.py
kuaipandriver/concurrent.py
kuaipandriver/httputils.py
kuaipandriver/kuaipanapi.py
kuaipandriver/kuaipanfuse.py
kuaipandriver/test.py
kuaipandriver.egg-info/PKG-INFO
kuaipandriver.egg-info/SOURCES.txt
kuaipandriver.egg-info/dependency_links.txt
kuaipandriver.egg-info/entry_points.txt
kuaipandriver.egg-info/requires.txt
kuaipandriver.egg-info/top_level.txt