Metadata-Version: 1.1
Name: kuaipandriver
Version: 0.5
Summary: A network driver's fuse Implementation base on kingsoft's kuaipan api
Home-page: https://github.com/alex8224/fuse_for_kuaipan
Author: alex8224@gmail.com, birdaccp@gmail.com
Author-email: alex8224@gmail.com, birdaccp@gmail.com
License: MIT
Keywords: fuse,kuaipan,network driver,mount
Platform: Linux
Classifier: License :: OSI Approved :: MIT License
Classifier: Programming Language :: Python :: 2
Classifier: Programming Language :: Python :: 2.6
Classifier: Programming Language :: Python :: 2.7
Classifier: Topic :: Utilities
